probctrl/__init__.py
probctrl-0.1.2.dist-info/licenses/LICENSE
probctrl-0.1.2.dist-info/METADATA
probctrl-0.1.2.dist-info/WHEEL
probctrl-0.1.2.dist-info/top_level.txt
probctrl-0.1.2.dist-info/RECORD
