Metadata-Version: 2.4
Name: probctrl
Version: 0.1.2
Summary: A lightweight Python decorator toolkit for probabilistic, delayed, and throttled execution.
Home-page: https://github.com/Lovelymili/probctrl
Author: Lovelymili
Author-email: 982074664@qq.com
License: MIT
Requires-Python: >=3.6
License-File: LICENSE
Dynamic: author
Dynamic: author-email
Dynamic: description
Dynamic: description-content-type
Dynamic: home-page
Dynamic: license
Dynamic: license-file
Dynamic: requires-python
Dynamic: summary
